lora_textnormalization/__init__.py
lora_textnormalization/normalization.py
lora_textnormalization-0.1.4.dist-info/WHEEL
lora_textnormalization-0.1.4.dist-info/METADATA
lora_textnormalization-0.1.4.dist-info/RECORD
