Metadata-Version: 2.1
Name: lora-textnormalization
Version: 0.1.4
Summary: A text normalization package for general English NLP tasks.
License: MIT
Author: Adrian-Wong
Author-email: adrian@asklora.ai
Requires-Python: >=3.7,<4.0
Classifier: License :: OSI Approved :: MIT License
Classifier: Programming Language :: Python :: 3
Classifier: Programming Language :: Python :: 3.7
Classifier: Programming Language :: Python :: 3.8
Classifier: Programming Language :: Python :: 3.9
Classifier: Programming Language :: Python :: 3.10
Classifier: Programming Language :: Python :: 3.11
Requires-Dist: spacy (>=3.4.2,<4.0.0)
